jupyter_ai_router/__init__.py
jupyter_ai_router/_version.py
jupyter_ai_router/extension.py
jupyter_ai_router/handlers.py
jupyter_ai_router/router.py
jupyter_ai_router/utils.py
jupyter_ai_router/labextension/build_log.json
jupyter_ai_router/labextension/package.json
jupyter_ai_router/labextension/static/lib_index_js.5096804212d049ea5d0f.js
jupyter_ai_router/labextension/static/lib_index_js.5096804212d049ea5d0f.js.map
jupyter_ai_router/labextension/static/remoteEntry.38ba37a3ed6dff8ab8a6.js
jupyter_ai_router/labextension/static/remoteEntry.38ba37a3ed6dff8ab8a6.js.map
jupyter_ai_router/labextension/static/style.js
jupyter_ai_router/labextension/static/style_index_js.4c98039395ea01e3db11.js
jupyter_ai_router/labextension/static/style_index_js.4c98039395ea01e3db11.js.map
jupyter_ai_router/tests/__init__.py
jupyter_ai_router/tests/test_handlers.py
jupyter_ai_router/tests/test_message_router.py
jupyter_ai_router-0.0.1.data/data/etc/jupyter/jupyter_server_config.d/jupyter_ai_router.json
jupyter_ai_router-0.0.1.data/data/share/jupyter/labextensions/@jupyter-ai/router/build_log.json
jupyter_ai_router-0.0.1.data/data/share/jupyter/labextensions/@jupyter-ai/router/package.json
jupyter_ai_router-0.0.1.data/data/share/jupyter/labextensions/@jupyter-ai/router/static/lib_index_js.5096804212d049ea5d0f.js
jupyter_ai_router-0.0.1.data/data/share/jupyter/labextensions/@jupyter-ai/router/static/lib_index_js.5096804212d049ea5d0f.js.map
jupyter_ai_router-0.0.1.data/data/share/jupyter/labextensions/@jupyter-ai/router/static/remoteEntry.38ba37a3ed6dff8ab8a6.js
jupyter_ai_router-0.0.1.data/data/share/jupyter/labextensions/@jupyter-ai/router/static/remoteEntry.38ba37a3ed6dff8ab8a6.js.map
jupyter_ai_router-0.0.1.data/data/share/jupyter/labextensions/@jupyter-ai/router/static/style.js
jupyter_ai_router-0.0.1.data/data/share/jupyter/labextensions/@jupyter-ai/router/static/style_index_js.4c98039395ea01e3db11.js
jupyter_ai_router-0.0.1.dist-info/METADATA
jupyter_ai_router-0.0.1.dist-info/WHEEL
jupyter_ai_router-0.0.1.dist-info/licenses/LICENSE
jupyter_ai_router-0.0.1.dist-info/RECORD
