Metadata-Version: 2.4
Name: jupyter_ai_router
Version: 0.0.1
Summary: Core routing layer of Jupyter AI
Project-URL: Homepage, https://github.com/jupyter-ai-contrib/jupyter-ai-router
Project-URL: Bug Tracker, https://github.com/jupyter-ai-contrib/jupyter-ai-router/issues
Project-URL: Repository, https://github.com/jupyter-ai-contrib/jupyter-ai-router.git
Author-email: Project Jupyter <jupyter@googlegroups.com>
License: BSD 3-Clause License
License-File: LICENSE
Keywords: jupyter,jupyterlab,jupyterlab-extension
Classifier: Framework :: Jupyter
Classifier: Framework :: Jupyter :: JupyterLab
Classifier: Framework :: Jupyter :: JupyterLab :: 4
Classifier: Framework :: Jupyter :: JupyterLab :: Extensions
Classifier: Framework :: Jupyter :: JupyterLab :: Extensions :: Prebuilt
Classifier: License :: OSI Approved :: BSD License
Classifier: Programming Language :: Python
Classifier: Programming Language :: Python :: 3
Classifier: Programming Language :: Python :: 3.9
Classifier: Programming Language :: Python :: 3.10
Classifier: Programming Language :: Python :: 3.11
Classifier: Programming Language :: Python :: 3.12
Classifier: Programming Language :: Python :: 3.13
Requires-Python: >=3.9
Requires-Dist: jupyter-collaboration>=4.0.0
Requires-Dist: jupyter-server<3,>=2.4.0
Requires-Dist: jupyterlab-chat>=0.17.0
Provides-Extra: test
Requires-Dist: coverage; extra == 'test'
Requires-Dist: pytest; extra == 'test'
Requires-Dist: pytest-asyncio; extra == 'test'
Requires-Dist: pytest-cov; extra == 'test'
Requires-Dist: pytest-jupyter[server]>=0.6.0; extra == 'test'
